trytond_gis/__init__.py
trytond_gis/const.py
trytond_gis/fields.py
trytond_gis/sql.py
trytond_gis/postgis/__init__.py
trytond_gis/postgis/database.py
trytond_gis/postgis/table.py
trytond_gis/tests/__init__.py
trytond_gis/tests/gis.py
trytond_gis/tests/test_fields.py
trytond_gis-7.8.0.dist-info/licenses/LICENSE
trytond_gis-7.8.0.dist-info/METADATA
trytond_gis-7.8.0.dist-info/WHEEL
trytond_gis-7.8.0.dist-info/entry_points.txt
trytond_gis-7.8.0.dist-info/top_level.txt
trytond_gis-7.8.0.dist-info/RECORD
